{"nodes":[{"nodeID":"8837","text":"analyses","type":"L","timestamp":"2012-12-07 12:21:49"},{"nodeID":"24610","text":"{P1 A0}   Yerkes and Lukas urge that the resemblance of an animal's nervous system and sense-organs to those of human beings ought to be taken into consideration in deciding whether the animal is conscious or not.","type":"I","timestamp":"2013-10-31 14:04:03"},{"nodeID":"24611","text":"{P2 A0}   Lukas suggests that the criteria of consciousness should be grouped under three heads : morphological, including the structure of the brain and sense- organs, physiological, and teleological.","type":"I","timestamp":"2013-10-31 14:04:03"},{"nodeID":"24612","text":"{P3 A0}   Yerkes proposes \"the following six criteria in what seems to me in general the order of increasing importance. The functional signs are of greater value as a rule than the structural ; and within each of the categories the particular sign is usually of more value than the general. In certain cases, however, it might be maintained that neural specialization is of greater importance than modifiability.","type":"I","timestamp":"2013-10-31 14:04:03"},{"nodeID":"24613","text":"{P4 A0}          I. Structural Criteria. 1. General form of organism (Organization). 2. Nervous system (Neural organization). 3. Specialization in the nervous system\u00a0(Neural specialization).","type":"I","timestamp":"2013-10-31 14:04:03"},{"nodeID":"24614","text":"{P5 A0}          II. Functional Criteria. 1. General form of reaction (Discrimination). 2. Modifiability of reaction (Docility). 3. Variability of reaction (Initiative)\" (463). The terms \"discrimination,\" \"docility,\" and \"initiative\" in this connection are borrowed from Royce's \"Outlines of Psychology \" (372).","type":"I","timestamp":"2013-10-31 14:04:03"},{"nodeID":"24615","text":"{P6 A0}    If resemblance of nervous and sense-organ structure to the human type is to be taken along with rapid learning as co- ordinate evidence of consciousness, it is clear that here also we have to deal with a matter of degree. The structure of the lower animals differs increasingly from our own as we go down the scale. At what degree of difference shall we draw the line and say that the animals above it may be conscious, but that those below it cannot be? No one could possibly establish such a line.","type":"I","timestamp":"2013-10-31 14:04:03"},{"nodeID":"24616","text":"{P7 A0}    The truth of the whole matter seems to be this : We can say neither what amount of resemblance in structure to human beings, nor what speed of learning, constitutes a definite mark distinguishing animals with minds from those without minds, unless we are prepared to assert that only animals which learn so fast that they must have memory ideas possess mind at all. And this would conflict with the argument from structure.","type":"I","timestamp":"2013-10-31 14:04:03"},{"nodeID":"24617","text":"{P8 A0}   For example, there is no good experimental evidence that cats possess ideas, yet there is enough analogy between their nervous systems and our own to make it improbable that consciousness, so complex and highly developed in us, is in them wholly lacking.","type":"I","timestamp":"2013-10-31 14:04:03"},{"nodeID":"24618","text":"{P9 A0}  We know not where consciousness begins in the animal world. We know where it surely resides in ourselves; we know where it exists beyond a reasonable doubt in those animals of structure resembling ours which rapidly adapt themselves to the lessons of experience. Beyond this point, for all we know, it may exist in simpler and simpler forms until we reach the very lowest of living beings.","type":"I","timestamp":"2013-10-31 14:04:03"},{"nodeID":"24619","text":"RA","type":"RA","timestamp":"2013-10-31 14:04:03"},{"nodeID":"24620","text":"RA","type":"RA","timestamp":"2013-10-31 14:04:03"},{"nodeID":"24621","text":"RA","type":"RA","timestamp":"2013-10-31 14:04:03"},{"nodeID":"24622","text":"RA","type":"RA","timestamp":"2013-10-31 14:04:03"},{"nodeID":"24623","text":"RA","type":"RA","timestamp":"2013-10-31 14:04:03"},{"nodeID":"24624","text":"RA","type":"RA","timestamp":"2013-10-31 14:04:03"},{"nodeID":"24625","text":"RA","type":"RA","timestamp":"2013-10-31 14:04:03"},{"nodeID":"24626","text":"RA","type":"RA","timestamp":"2013-10-31 14:04:03"},{"nodeID":"24627","text":"Animal Mind Arg15","type":"I","timestamp":"2013-10-31 14:04:03"}],"edges":[{"edgeID":"24293","fromID":"8837","toID":"24610","formEdgeID":null},{"edgeID":"24294","fromID":"8837","toID":"24611","formEdgeID":null},{"edgeID":"24295","fromID":"8837","toID":"24612","formEdgeID":null},{"edgeID":"24296","fromID":"8837","toID":"24613","formEdgeID":null},{"edgeID":"24297","fromID":"8837","toID":"24614","formEdgeID":null},{"edgeID":"24298","fromID":"8837","toID":"24615","formEdgeID":null},{"edgeID":"24299","fromID":"8837","toID":"24616","formEdgeID":null},{"edgeID":"24300","fromID":"8837","toID":"24617","formEdgeID":null},{"edgeID":"24301","fromID":"8837","toID":"24618","formEdgeID":null},{"edgeID":"24303","fromID":"8837","toID":"24619","formEdgeID":null},{"edgeID":"24306","fromID":"8837","toID":"24620","formEdgeID":null},{"edgeID":"24309","fromID":"8837","toID":"24621","formEdgeID":null},{"edgeID":"24312","fromID":"8837","toID":"24622","formEdgeID":null},{"edgeID":"24315","fromID":"8837","toID":"24623","formEdgeID":null},{"edgeID":"24318","fromID":"8837","toID":"24624","formEdgeID":null},{"edgeID":"24321","fromID":"8837","toID":"24625","formEdgeID":null},{"edgeID":"24324","fromID":"8837","toID":"24626","formEdgeID":null},{"edgeID":"32170","fromID":"8837","toID":"8837","formEdgeID":null},{"edgeID":"24314","fromID":"24610","toID":"24623","formEdgeID":null},{"edgeID":"24302","fromID":"24611","toID":"24619","formEdgeID":null},{"edgeID":"24305","fromID":"24612","toID":"24620","formEdgeID":null},{"edgeID":"24308","fromID":"24613","toID":"24621","formEdgeID":null},{"edgeID":"24311","fromID":"24614","toID":"24622","formEdgeID":null},{"edgeID":"24317","fromID":"24615","toID":"24624","formEdgeID":null},{"edgeID":"24323","fromID":"24616","toID":"24626","formEdgeID":null},{"edgeID":"24320","fromID":"24617","toID":"24625","formEdgeID":null},{"edgeID":"24304","fromID":"24619","toID":"24610","formEdgeID":null},{"edgeID":"24307","fromID":"24620","toID":"24610","formEdgeID":null},{"edgeID":"24310","fromID":"24621","toID":"24612","formEdgeID":null},{"edgeID":"24313","fromID":"24622","toID":"24612","formEdgeID":null},{"edgeID":"24316","fromID":"24623","toID":"24615","formEdgeID":null},{"edgeID":"24319","fromID":"24624","toID":"24616","formEdgeID":null},{"edgeID":"24322","fromID":"24625","toID":"24616","formEdgeID":null},{"edgeID":"24325","fromID":"24626","toID":"24618","formEdgeID":null}],"locutions":[{"nodeID":"8837","personID":"488","timestamp":"2014-02-19 11:54:58","start":null,"end":null,"source":null},{"nodeID":"8837","personID":"0","timestamp":"2015-11-11 11:38:52","start":null,"end":null,"source":null},{"nodeID":"8837","personID":"0","timestamp":"2015-11-11 11:38:53","start":null,"end":null,"source":null},{"nodeID":"8837","personID":"0","timestamp":"2015-11-11 11:39:16","start":null,"end":null,"source":null},{"nodeID":"8837","personID":"0","timestamp":"2015-11-11 11:39:17","start":null,"end":null,"source":null},{"nodeID":"8837","personID":"0","timestamp":"2017-06-14 13:26:42","start":null,"end":null,"source":null},{"nodeID":"8837","personID":"0","timestamp":"2017-10-31 14:43:29","start":null,"end":null,"source":null}]}