{"nodes":[{"nodeID":"129480","text":"Management: Our goal is to maximize profit.","type":"I","timestamp":"2016-02-27 12:36:52"},{"nodeID":"129481","text":"Management: Cutting costs is the best way to increase profit.","type":"I","timestamp":"2016-02-27 12:36:52"},{"nodeID":"129482","text":"Management: We need to cut application costs.","type":"I","timestamp":"2016-02-27 12:36:52"},{"nodeID":"129483","text":"Default Inference","type":"RA","timestamp":"2016-02-27 12:36:52","scheme":"Default Inference","schemeID":"72"},{"nodeID":"129484","text":"Admin: We want to be as productive as possible","type":"I","timestamp":"2016-02-27 12:36:52"},{"nodeID":"129485","text":"Management: Best way to cut application cost is reducing software licence costs.","type":"I","timestamp":"2016-02-27 12:36:52"},{"nodeID":"129486","text":"Management: We need to have a free software package.","type":"I","timestamp":"2016-02-27 12:36:52"},{"nodeID":"129487","text":"Default Inference","type":"RA","timestamp":"2016-02-27 12:36:53","scheme":"Default Inference","schemeID":"72"},{"nodeID":"129488","text":"Admin: We find it difficult to adapt to new software","type":"I","timestamp":"2016-02-27 12:36:53"},{"nodeID":"129489","text":"Admin: We do not want new software unless it is similar to MS Office","type":"I","timestamp":"2016-02-27 12:36:53"},{"nodeID":"129490","text":"Default Inference","type":"RA","timestamp":"2016-02-27 12:36:53","scheme":"Default Inference","schemeID":"72"},{"nodeID":"129491","text":"IT: We want to have the best IT in place.","type":"I","timestamp":"2016-02-27 12:36:53"},{"nodeID":"129492","text":"IT: Software which is around for longer than 10 years is proven quality software.","type":"I","timestamp":"2016-02-27 12:36:53"},{"nodeID":"129493","text":"IT: We should have Software which is longer around than 10 years.","type":"I","timestamp":"2016-02-27 12:36:53"},{"nodeID":"129494","text":"Default Inference","type":"RA","timestamp":"2016-02-27 12:36:53","scheme":"Default Inference","schemeID":"72"},{"nodeID":"129495","text":"ArchiTeam: We want to meet the requirements of all stakeholders.","type":"I","timestamp":"2016-02-27 12:36:53"},{"nodeID":"129496","text":"ArchiTeam: OO is a free software package.","type":"I","timestamp":"2016-02-27 12:36:53"},{"nodeID":"129497","text":"ArchiTeam: OO is similar to MS Office.","type":"I","timestamp":"2016-02-27 12:36:53"},{"nodeID":"129498","text":"ArchiTeam: OO conforms to the Management requirements.","type":"I","timestamp":"2016-02-27 12:36:53"},{"nodeID":"129499","text":"Default Inference","type":"RA","timestamp":"2016-02-27 12:36:53","scheme":"Default Inference","schemeID":"72"},{"nodeID":"129500","text":"ArchiTeam: OO conforms to the Admin requirements.","type":"I","timestamp":"2016-02-27 12:36:53"},{"nodeID":"129501","text":"Default Inference","type":"RA","timestamp":"2016-02-27 12:36:53","scheme":"Default Inference","schemeID":"72"},{"nodeID":"129502","text":"ArchiTeam: OO is proven software.","type":"I","timestamp":"2016-02-27 12:36:53"},{"nodeID":"129503","text":"ArchiTeam: OO conforms to the Admin requirements","type":"I","timestamp":"2016-02-27 12:36:53"},{"nodeID":"129504","text":"Default Inference","type":"RA","timestamp":"2016-02-27 12:36:53","scheme":"Default Inference","schemeID":"72"},{"nodeID":"129505","text":"ArchiTeam: OO conforms to the requirements of all stakeholders.","type":"I","timestamp":"2016-02-27 12:36:53"},{"nodeID":"129506","text":"Default Inference","type":"RA","timestamp":"2016-02-27 12:36:54","scheme":"Default Inference","schemeID":"72"},{"nodeID":"129507","text":"ArchiTeam: We should choose OO.","type":"I","timestamp":"2016-02-27 12:36:54"},{"nodeID":"129508","text":"Default Inference","type":"RA","timestamp":"2016-02-27 12:36:54","scheme":"Default Inference","schemeID":"72"}],"edges":[{"edgeID":"170556","fromID":"129480","toID":"129483","formEdgeID":null},{"edgeID":"170558","fromID":"129481","toID":"129483","formEdgeID":null},{"edgeID":"170561","fromID":"129482","toID":"129487","formEdgeID":null},{"edgeID":"170557","fromID":"129483","toID":"129482","formEdgeID":null},{"edgeID":"170562","fromID":"129484","toID":"129490","formEdgeID":null},{"edgeID":"170559","fromID":"129485","toID":"129487","formEdgeID":null},{"edgeID":"170568","fromID":"129486","toID":"129499","formEdgeID":null},{"edgeID":"170560","fromID":"129487","toID":"129486","formEdgeID":null},{"edgeID":"170564","fromID":"129488","toID":"129490","formEdgeID":null},{"edgeID":"170571","fromID":"129489","toID":"129501","formEdgeID":null},{"edgeID":"170563","fromID":"129490","toID":"129489","formEdgeID":null},{"edgeID":"170565","fromID":"129491","toID":"129494","formEdgeID":null},{"edgeID":"170567","fromID":"129492","toID":"129494","formEdgeID":null},{"edgeID":"170576","fromID":"129493","toID":"129504","formEdgeID":null},{"edgeID":"170566","fromID":"129494","toID":"129493","formEdgeID":null},{"edgeID":"170581","fromID":"129495","toID":"129508","formEdgeID":null},{"edgeID":"170570","fromID":"129496","toID":"129499","formEdgeID":null},{"edgeID":"170573","fromID":"129497","toID":"129501","formEdgeID":null},{"edgeID":"170580","fromID":"129498","toID":"129506","formEdgeID":null},{"edgeID":"170569","fromID":"129499","toID":"129498","formEdgeID":null},{"edgeID":"170577","fromID":"129500","toID":"129506","formEdgeID":null},{"edgeID":"170572","fromID":"129501","toID":"129500","formEdgeID":null},{"edgeID":"170574","fromID":"129502","toID":"129504","formEdgeID":null},{"edgeID":"170579","fromID":"129503","toID":"129506","formEdgeID":null},{"edgeID":"170575","fromID":"129504","toID":"129503","formEdgeID":null},{"edgeID":"170583","fromID":"129505","toID":"129508","formEdgeID":null},{"edgeID":"170578","fromID":"129506","toID":"129505","formEdgeID":null},{"edgeID":"170582","fromID":"129508","toID":"129507","formEdgeID":null}],"locutions":[]}