{"nodes":[{"nodeID":"129121","text":"The IT department does not mind introducing a new software package","type":"I","timestamp":"2016-02-25 12:55:38"},{"nodeID":"131284","text":"GeneriCo\u2019s admin department finds it difficult to adapt to new software","type":"I","timestamp":"2016-03-01 11:16:26"},{"nodeID":"262111","text":"GeneriCo\u2019s management has decided that cutting costs is the best way to increase profit","type":"I","timestamp":"2017-02-28 11:06:37"},{"nodeID":"262135","text":"GeneriCo, like most companies, is driven by profit.","type":"I","timestamp":"2017-03-01 12:24:53"},{"nodeID":"262145","text":"An external IT consultant from Zoho argues that the best software package that is cheaper than the current (MS Office), is Zoho\u2019s cloud-based solution.","type":"I","timestamp":"2017-03-01 12:46:45"},{"nodeID":"262156","text":"One of the management team\u2019s members argues that Generico should become more green, and that profit should not be the main driver anymore.","type":"I","timestamp":"2017-03-01 12:50:38"},{"nodeID":"263044","text":"The architecture team thinks that OpenOffice is a good candidate for replacing Office","type":"I","timestamp":"2017-03-07 15:02:47"},{"nodeID":"263287","text":"the best way to achieve this is to cut application costs by paying less for software licenses.","type":"I","timestamp":"2017-03-07 17:50:42"},{"nodeID":"263288","text":"GeneriCo therefore needs a free software\u00a0package.","type":"I","timestamp":"2017-03-07 17:50:42"},{"nodeID":"263289","text":"they would want the software packages to be kept the same.","type":"I","timestamp":"2017-03-07 17:50:43"},{"nodeID":"263290","text":"they at least do not want to spend a lot of time learning the workings of the new package","type":"I","timestamp":"2017-03-07 17:50:43"},{"nodeID":"263291","text":"so any new software should be similar to the MS Office software they currently use.","type":"I","timestamp":"2017-03-07 17:50:43"},{"nodeID":"263292","text":"as it conforms to all the requirements and constraints laid out by the stakeholders.","type":"I","timestamp":"2017-03-07 17:50:43"},{"nodeID":"263293","text":"Default Inference","type":"RA","timestamp":"2017-03-07 17:50:43","scheme":"Default Inference","schemeID":"72"},{"nodeID":"263294","text":"Default Inference","type":"RA","timestamp":"2017-03-07 17:50:43","scheme":"Default Inference","schemeID":"72"},{"nodeID":"263295","text":"Default Inference","type":"RA","timestamp":"2017-03-07 17:50:43","scheme":"Default Inference","schemeID":"72"},{"nodeID":"263296","text":"Default Conflict","type":"CA","timestamp":"2017-03-07 17:50:44","scheme":"Default Conflict","schemeID":"71"},{"nodeID":"263297","text":"Default Inference","type":"RA","timestamp":"2017-03-07 17:50:44","scheme":"Default Inference","schemeID":"72"},{"nodeID":"263298","text":"Default Inference","type":"RA","timestamp":"2017-03-07 17:50:44","scheme":"Default Inference","schemeID":"72"},{"nodeID":"263299","text":"but they would like a mature software package \u2013 more specifically, a package which has been around for at least 10 years.","type":"I","timestamp":"2017-03-07 17:50:44"},{"nodeID":"263300","text":"Default Inference","type":"RA","timestamp":"2017-03-07 17:50:44","scheme":"Default Inference","schemeID":"72"},{"nodeID":"263301","text":"Paying less for software licenses does not necessarily mean the use of free software packges.","type":"I","timestamp":"2017-03-07 17:50:44"},{"nodeID":"263302","text":"Default Conflict","type":"CA","timestamp":"2017-03-07 17:50:45","scheme":"Default Conflict","schemeID":"71"},{"nodeID":"263303","text":"Default Inference","type":"RA","timestamp":"2017-03-07 17:50:45","scheme":"Default Inference","schemeID":"72"},{"nodeID":"263304","text":"Default Inference","type":"RA","timestamp":"2017-03-07 17:50:45","scheme":"Default Inference","schemeID":"72"},{"nodeID":"263305","text":"Default Inference","type":"RA","timestamp":"2017-03-07 17:50:45","scheme":"Default Inference","schemeID":"72"},{"nodeID":"263306","text":"Alternative Means","type":"CA","timestamp":"2017-03-07 17:50:45","scheme":"AlternativeMeans","schemeID":"34"},{"nodeID":"263307","text":"Default Inference","type":"RA","timestamp":"2017-03-07 17:50:45","scheme":"Default Inference","schemeID":"72"},{"nodeID":"263308","text":"Default Inference","type":"RA","timestamp":"2017-03-07 17:50:45","scheme":"Default Inference","schemeID":"72"},{"nodeID":"263309","text":"Default Inference","type":"RA","timestamp":"2017-03-07 17:50:46","scheme":"Default Inference","schemeID":"72"},{"nodeID":"263310","text":"Conflicting Goals","type":"CA","timestamp":"2017-03-07 17:50:46","scheme":"ConflictingGoals","schemeID":"39"},{"nodeID":"263311","text":"The head of GeneriCo\u2019s finance has done some calculations, and it turns out that cutting app costs does in fact not decrease costs in the foreseeable future: the migration costs are so high that any yearly savings pale in comparison.","type":"I","timestamp":"2017-03-07 17:50:46"},{"nodeID":"263312","text":"Default Conflict","type":"CA","timestamp":"2017-03-07 17:50:46","scheme":"Default Conflict","schemeID":"71"}],"edges":[{"edgeID":"317947","fromID":"129121","toID":"263300","formEdgeID":null},{"edgeID":"317951","fromID":"129121","toID":"263303","formEdgeID":null},{"edgeID":"317945","fromID":"131284","toID":"263298","formEdgeID":null},{"edgeID":"317953","fromID":"131284","toID":"263304","formEdgeID":null},{"edgeID":"317937","fromID":"262111","toID":"263294","formEdgeID":null},{"edgeID":"317935","fromID":"262135","toID":"263293","formEdgeID":null},{"edgeID":"317957","fromID":"262145","toID":"263306","formEdgeID":null},{"edgeID":"317965","fromID":"262156","toID":"263310","formEdgeID":null},{"edgeID":"317939","fromID":"263287","toID":"263295","formEdgeID":null},{"edgeID":"317959","fromID":"263288","toID":"263307","formEdgeID":null},{"edgeID":"317941","fromID":"263289","toID":"263296","formEdgeID":null},{"edgeID":"317943","fromID":"263290","toID":"263297","formEdgeID":null},{"edgeID":"317963","fromID":"263291","toID":"263309","formEdgeID":null},{"edgeID":"317955","fromID":"263292","toID":"263305","formEdgeID":null},{"edgeID":"317936","fromID":"263293","toID":"262111","formEdgeID":null},{"edgeID":"317938","fromID":"263294","toID":"263287","formEdgeID":null},{"edgeID":"317940","fromID":"263295","toID":"263288","formEdgeID":null},{"edgeID":"317942","fromID":"263296","toID":"263288","formEdgeID":null},{"edgeID":"317944","fromID":"263297","toID":"263291","formEdgeID":null},{"edgeID":"317946","fromID":"263298","toID":"263289","formEdgeID":null},{"edgeID":"317961","fromID":"263299","toID":"263308","formEdgeID":null},{"edgeID":"317948","fromID":"263300","toID":"263299","formEdgeID":null},{"edgeID":"317949","fromID":"263301","toID":"263302","formEdgeID":null},{"edgeID":"317950","fromID":"263302","toID":"263288","formEdgeID":null},{"edgeID":"317952","fromID":"263303","toID":"263288","formEdgeID":null},{"edgeID":"317954","fromID":"263304","toID":"263290","formEdgeID":null},{"edgeID":"317956","fromID":"263305","toID":"263044","formEdgeID":null},{"edgeID":"317958","fromID":"263306","toID":"263044","formEdgeID":null},{"edgeID":"317960","fromID":"263307","toID":"263292","formEdgeID":null},{"edgeID":"317962","fromID":"263308","toID":"263292","formEdgeID":null},{"edgeID":"317964","fromID":"263309","toID":"263292","formEdgeID":null},{"edgeID":"317966","fromID":"263310","toID":"262111","formEdgeID":null},{"edgeID":"317967","fromID":"263311","toID":"263312","formEdgeID":null},{"edgeID":"317968","fromID":"263312","toID":"263288","formEdgeID":null}],"locutions":[]}